nested_wrap/__init__.py
nested_wrap/wrap.py
nested_wrap-0.0.1.dist-info/LICENSE
nested_wrap-0.0.1.dist-info/METADATA
nested_wrap-0.0.1.dist-info/WHEEL
nested_wrap-0.0.1.dist-info/top_level.txt
nested_wrap-0.0.1.dist-info/RECORD
