Metadata-Version: 2.1
Name: nested-wrap
Version: 0.0.1
Summary: wrap_func_with_nested_access
Home-page: 
Author: simplew
Author-email: simplew@211.com
Classifier: Programming Language :: Python :: 3
Classifier: License :: OSI Approved :: MIT License
Classifier: Operating System :: OS Independent
License-File: LICENSE
